Metadata-Version: 1.1
Name: girder-table-view
Version: 0.2.0a1
Summary: Render table view in the item page for CSV and TSV files.
Home-page: http://girder.readthedocs.io/en/latest/plugins.html#table-view
Author: Kitware, Inc.
Author-email: kitware@kitware.com
License: Apache 2.0
Platform: UNKNOWN
Classifier: Development Status :: 4 - Beta
Classifier: Environment :: Web Environment
Classifier: License :: OSI Approved :: Apache Software License
Classifier: Operating System :: OS Independent
Classifier: Programming Language :: Python
Classifier: Programming Language :: Python :: 2
Classifier: Programming Language :: Python :: 2.7
Classifier: Programming Language :: Python :: 3
Classifier: Programming Language :: Python :: 3.5
